fasthep_toolbench/__init__.py
fasthep_toolbench/_version.py
fasthep_toolbench/_version.pyi
fasthep_toolbench/logger.py
fasthep_toolbench/misc.py
fasthep_toolbench/py.typed
fasthep_toolbench/display/__init__.py
fasthep_toolbench/display/console.py
fasthep_toolbench/http/__init__.py
fasthep_toolbench/http/download.py
fasthep_toolbench/package/__init__.py
fasthep_toolbench/package/_import.py
fasthep_toolbench/package/_version.py
fasthep_toolbench-2025.6.2.dist-info/METADATA
fasthep_toolbench-2025.6.2.dist-info/WHEEL
fasthep_toolbench-2025.6.2.dist-info/licenses/LICENSE
fasthep_toolbench-2025.6.2.dist-info/RECORD
