Metadata-Version: 2.4
Name: fasthep-toolbench
Version: 2025.6.2
Summary: Package for cross-package utility functions
Project-URL: Homepage, https://github.com/FAST-HEP/fasthep-toolbench
Project-URL: Bug Tracker, https://github.com/FAST-HEP/fasthep-toolbench/issues
Project-URL: Discussions, https://github.com/FAST-HEP/fasthep-toolbench/discussions
Project-URL: Changelog, https://github.com/FAST-HEP/fasthep-toolbench/releases
Author-email: Luke Kreczko <kreczko@cern.ch>
License-Expression: Apache-2.0
License-File: LICENSE
Classifier: Development Status :: 1 - Planning
Classifier: Intended Audience :: Developers
Classifier: Intended Audience :: Science/Research
Classifier: Operating System :: OS Independent
Classifier: Programming Language :: Python
Classifier: Programming Language :: Python :: 3
Classifier: Programming Language :: Python :: 3 :: Only
Classifier: Programming Language :: Python :: 3.11
Classifier: Programming Language :: Python :: 3.12
Classifier: Programming Language :: Python :: 3.13
Classifier: Topic :: Scientific/Engineering
Classifier: Typing :: Typed
Requires-Python: >=3.11
Requires-Dist: httpx
Requires-Dist: loguru
Requires-Dist: rich
Requires-Dist: tabulate
Provides-Extra: dev
Requires-Dist: pytest-cov>=3; extra == 'dev'
Requires-Dist: pytest>=6; extra == 'dev'
Provides-Extra: docs
Requires-Dist: furo>=2023.08.17; extra == 'docs'
Requires-Dist: myst-parser>=0.13; extra == 'docs'
Requires-Dist: sphinx-autodoc-typehints; extra == 'docs'
Requires-Dist: sphinx-copybutton; extra == 'docs'
Requires-Dist: sphinx>=7.0; extra == 'docs'
Provides-Extra: test
Requires-Dist: pytest-cov>=3; extra == 'test'
Requires-Dist: pytest>=6; extra == 'test'
